README.md
setup.py
HTTPReplay.egg-info/PKG-INFO
HTTPReplay.egg-info/SOURCES.txt
HTTPReplay.egg-info/dependency_links.txt
HTTPReplay.egg-info/entry_points.txt
HTTPReplay.egg-info/requires.txt
HTTPReplay.egg-info/top_level.txt
httpreplay/__init__.py
httpreplay/cobweb.py
httpreplay/cut.py
httpreplay/exceptions.py
httpreplay/main.py
httpreplay/misc.py
httpreplay/reader.py
httpreplay/shoddy.py
httpreplay/smegma.py
httpreplay/utils.py