Metadata-Version: 2.1
Name: HTTPReplay
Version: 0.2.5
Summary: Properly interpret, decrypt, and replay pcap files
Home-page: UNKNOWN
Author: Hatching B.V.
Author-email: info@hatching.io
License: GPLv3
Platform: UNKNOWN
Provides-Extra: mitmproxy
Provides-Extra: dev
